pydatev/__init__.py
pydatev/app/__init__.py
pydatev/app/config.py
pydatev/app/main.py
pydatev/app/models.py
pydatev/app/streamlit_app.py
pydatev/app/models/__init__.py
pydatev/app/models/base.py
pydatev/app/models/cash_register.py
pydatev/app/models/clients.py
pydatev/app/models/documents.py
pydatev/app/models/hr_eau.py
pydatev/app/models/hr_exports.py
pydatev/app/models/hr_files.py
pydatev/app/models/hr_jobs.py
pydatev/app/models/hr_payroll.py
pydatev/app/models/jobs.py
pydatev/app/models/master_data.py
pydatev/app/models/tenants.py
pydatev/app/routers/dependencies.py
pydatev/app/routers/hr_eau.py
pydatev/app/routers/hr_exports.py
pydatev/app/routers/hr_files.py
pydatev/app/routers/hr_payroll.py
pydatev-0.1.0.dist-info/METADATA
pydatev-0.1.0.dist-info/WHEEL
pydatev-0.1.0.dist-info/RECORD
