Metadata-Version: 2.4
Name: pydatev
Version: 0.1.0
Summary: DATEV API Integration with FastAPI backend and Streamlit frontend
Project-URL: Homepage, https://github.com/superpandas-ai/pydatev
Project-URL: Repository, https://github.com/superpandas-ai/pydatev
Author-email: Haris Jabbar <haris@superpandas.ai>
License-Expression: MIT
Classifier: Development Status :: 3 - Alpha
Classifier: Intended Audience :: Developers
Classifier: License :: OSI Approved :: MIT License
Classifier: Programming Language :: Python :: 3.8
Requires-Python: >=3.8
Requires-Dist: aiofiles>=23.2.1
Requires-Dist: fastapi>=0.104.0
Requires-Dist: httpx>=0.25.0
Requires-Dist: pandas
Requires-Dist: pydantic-settings>=2.0.3
Requires-Dist: pydantic>=2.4.2
Requires-Dist: python-dotenv>=1.0.0
Requires-Dist: python-jose[cryptography]>=3.3.0
Requires-Dist: python-multipart>=0.0.6
Requires-Dist: streamlit
Requires-Dist: uvicorn>=0.24.0
Provides-Extra: dev
Requires-Dist: black>=21.0; extra == 'dev'
Requires-Dist: flake8>=3.9; extra == 'dev'
Requires-Dist: pytest-asyncio>=0.14.0; extra == 'dev'
Requires-Dist: pytest-cov>=2.10.0; extra == 'dev'
Requires-Dist: pytest>=6.0; extra == 'dev'
